MANIFEST.in
README.md
setup.py
address_net.egg-info/PKG-INFO
address_net.egg-info/SOURCES.txt
address_net.egg-info/dependency_links.txt
address_net.egg-info/requires.txt
address_net.egg-info/top_level.txt
addressnet/__init__.py
addressnet/dataset.py
addressnet/lookups.py
addressnet/model.py
addressnet/predict.py
addressnet/typo.py
addressnet/pretrained/__init__.py
addressnet/pretrained/checkpoint
addressnet/pretrained/graph.pbtxt
addressnet/pretrained/model.ckpt.data-00000-of-00001
addressnet/pretrained/model.ckpt.index
addressnet/pretrained/model.ckpt.meta